tail_toolkit/__init__.py
tail_toolkit/data/__init__.py
tail_toolkit/data/tail-toolkit.json
tail_toolkit/data/helps/tail.txt
tail_toolkit/modules/__init__.py
tail_toolkit/modules/cli.py
tail_toolkit/modules/conf.py
tail_toolkit/modules/logger.py
tail_toolkit/modules/tail.py
tail_toolkit/modules/utils.py
tail_toolkit-0.0.7.data/scripts/tt
tail_toolkit-0.0.7.dist-info/DESCRIPTION.rst
tail_toolkit-0.0.7.dist-info/METADATA
tail_toolkit-0.0.7.dist-info/RECORD
tail_toolkit-0.0.7.dist-info/WHEEL
tail_toolkit-0.0.7.dist-info/metadata.json
tail_toolkit-0.0.7.dist-info/top_level.txt
