Metadata-Version: 2.0
Name: tail-toolkit
Version: 0.0.7
Summary: An AWS tail command line interface (CLI). It helps you in tail some resoruces inside aws.
Home-page: https://github.com/lucioveloso/tail-toolkit
Author: Lucio Veloso Guimaraes
Author-email: UNKNOWN
License: UNKNOWN
Platform: UNKNOWN
Classifier: Development Status :: 4 - Beta
Classifier: Intended Audience :: Developers
Classifier: Intended Audience :: System Administrators
Classifier: Natural Language :: English
Classifier: License :: OSI Approved :: Apache Software License
Classifier: Programming Language :: Python
Classifier: Programming Language :: Python :: 2
Classifier: Programming Language :: Python :: 3
Requires-Dist: boto3 (>=1.4.4)
Requires-Dist: botocore (>=1.5.78)
